alphafoldmodel/AlphafoldModel.py
alphafoldmodel/LoadedKDTree.py
alphafoldmodel/ModelPAE.py
alphafoldmodel/ModelPDB.py
alphafoldmodel/__init__.py
alphafoldmodel-1.0.3.dist-info/METADATA
alphafoldmodel-1.0.3.dist-info/WHEEL
alphafoldmodel-1.0.3.dist-info/licenses/LICENSE.txt
alphafoldmodel-1.0.3.dist-info/RECORD
