Metadata-Version: 2.1
Name: alphafoldmodel
Version: 1.0.3
Summary: A package of Python objects for parsing and interacting with Alphafold models.
Project-URL: Homepage, https://github.com/Levurmion/AlphafoldModel
Author-email: Elbert Timothy <elberttimothy23@gmail.com>
License-File: LICENSE.txt
Classifier: License :: OSI Approved :: MIT License
Classifier: Operating System :: OS Independent
Classifier: Programming Language :: Python :: 3
Requires-Python: >=3.10
Requires-Dist: numpy
Requires-Dist: scipy
